researchkit/__init__.py
researchkit/sdk/__init__.py
researchkit/sdk/client.py
researchkit/shared/__init__.py
researchkit/shared/schemas.py
research_agent_kit-0.1.6.dist-info/METADATA
research_agent_kit-0.1.6.dist-info/WHEEL
research_agent_kit-0.1.6.dist-info/top_level.txt
research_agent_kit-0.1.6.dist-info/RECORD
