Metadata-Version: 2.4
Name: research-agent-kit
Version: 0.1.6
Summary: Research API and SDK
Requires-Python: >=3.10
Requires-Dist: httpx>=0.24
Requires-Dist: pydantic>=2.0
Provides-Extra: api
Requires-Dist: fastapi>=0.100; extra == "api"
Requires-Dist: uvicorn>=0.23; extra == "api"
Requires-Dist: python-dotenv>=1.0; extra == "api"
Requires-Dist: openrouter-provider; extra == "api"
Requires-Dist: engines4ai; extra == "api"
Requires-Dist: scraper4ai; extra == "api"
Requires-Dist: youtube-transcript-api; extra == "api"
Requires-Dist: pillow; extra == "api"
Requires-Dist: requests; extra == "api"
Provides-Extra: dev
Requires-Dist: build; extra == "dev"
Requires-Dist: twine; extra == "dev"
